egytech_fyi_wrapper/__init__.py
egytech_fyi_wrapper/config.toml
egytech_fyi_wrapper/core.py
egytech_fyi_wrapper/models.py
egytech_fyi_wrapper-1.1.6.dist-info/METADATA
egytech_fyi_wrapper-1.1.6.dist-info/WHEEL
egytech_fyi_wrapper-1.1.6.dist-info/licenses/LICENSE
egytech_fyi_wrapper-1.1.6.dist-info/RECORD
