Metadata-Version: 2.3
Name: egytech_fyi_wrapper
Version: 1.1.6
Summary: A Python API Wrapper for the EgyTech.FYI API
Author-email: Abdulrahman Mustafa Abdulrahman <abdulrahman.m.khaled@outlook.com>
License: MIT License
License-File: LICENSE
Classifier: License :: OSI Approved :: MIT License
Classifier: Operating System :: OS Independent
Classifier: Programming Language :: Python :: 3
Requires-Python: >=3.10
Requires-Dist: httpx
Requires-Dist: pandas
Requires-Dist: pydantic==2.7.3
Requires-Dist: tomli
Requires-Dist: xlsxwriter
